conveyor/__init__.py
conveyor/grpc.py
conveyor/py.typed
conveyor/secrets.py
conveyor/types.py
conveyor/auth/__init__.py
conveyor/auth/auth.py
conveyor/pb/application_runs_pb2.py
conveyor/pb/application_runs_pb2.pyi
conveyor/pb/application_runs_pb2_grpc.py
conveyor/pb/common_pb2.py
conveyor/pb/common_pb2.pyi
conveyor/pb/common_pb2_grpc.py
conveyor/pb/datafy_pb2.py
conveyor/pb/datafy_pb2.pyi
conveyor/pb/datafy_pb2_grpc.py
conveyor/pb/ide_pb2.py
conveyor/pb/ide_pb2.pyi
conveyor/pb/ide_pb2_grpc.py
conveyor/pb/notebook_pb2.py
conveyor/pb/notebook_pb2.pyi
conveyor/pb/notebook_pb2_grpc.py
conveyor/pb/packages_pb2.py
conveyor/pb/packages_pb2.pyi
conveyor/pb/packages_pb2_grpc.py
conveyor/pb/tag_pb2.py
conveyor/pb/tag_pb2.pyi
conveyor/pb/tag_pb2_grpc.py
conveyor/pb/buf/validate/validate_pb2.py
conveyor/pb/buf/validate/validate_pb2.pyi
conveyor/pb/buf/validate/validate_pb2_grpc.py
conveyor/pb/protoc_gen_openapiv2/options/annotations_pb2.py
conveyor/pb/protoc_gen_openapiv2/options/annotations_pb2.pyi
conveyor/pb/protoc_gen_openapiv2/options/annotations_pb2_grpc.py
conveyor/pb/protoc_gen_openapiv2/options/openapiv2_pb2.py
conveyor/pb/protoc_gen_openapiv2/options/openapiv2_pb2.pyi
conveyor/pb/protoc_gen_openapiv2/options/openapiv2_pb2_grpc.py
conveyor/pb/tagger/tagger_pb2.py
conveyor/pb/tagger/tagger_pb2.pyi
conveyor/pb/tagger/tagger_pb2_grpc.py
conveyor/project/__init__.py
conveyor/project/build.py
conveyor/project/project.py
conveyor/runner/__init__.py
conveyor/runner/container_task_runner.py
conveyor/runner/spark_task_runner.py
conveyor/runner/task_runner.py
conveyor/runner/task_state.py
conveyor/runner/task_submitter.py
sdk_conveyor-0.0.12.dist-info/METADATA
sdk_conveyor-0.0.12.dist-info/WHEEL
sdk_conveyor-0.0.12.dist-info/top_level.txt
sdk_conveyor-0.0.12.dist-info/RECORD
