Metadata-Version: 2.4
Name: sdk-conveyor
Version: 0.0.12
Summary: Python SDK for Conveyor
Author-email: Conveyor <support@conveyordata.com>
Project-URL: Homepage, https://conveyordata.com
Project-URL: Bug Tracker, https://github.com/datamindedbe/conveyor-roadmap/issues
Classifier: Development Status :: 4 - Beta
Classifier: Intended Audience :: Developers
Classifier: Operating System :: OS Independent
Classifier: Programming Language :: Python
Classifier: Programming Language :: Python :: 3
Classifier: Programming Language :: Python :: 3.10
Classifier: Programming Language :: Python :: 3.11
Classifier: Programming Language :: Python :: 3.12
Requires-Python: >=3.10
Requires-Dist: googleapis-common-protos<2.0.0,>=1.66.0
Requires-Dist: grpcio<2.0.0,>=1.74.0
Requires-Dist: protobuf<7.0.0,>=6.30.0
Requires-Dist: packaging>=21.3
